django_db_introspection-0.2.dist-info/DESCRIPTION.rst
django_db_introspection-0.2.dist-info/METADATA
django_db_introspection-0.2.dist-info/RECORD
django_db_introspection-0.2.dist-info/WHEEL
django_db_introspection-0.2.dist-info/metadata.json
django_db_introspection-0.2.dist-info/top_level.txt
migrations/__init__.py
