Metadata-Version: 2.0
Name: django-db-introspection
Version: 0.2
Summary: Django database introspection tool, through the data table name can dynamically create a Django models ready-to-use objects.
Home-page: https://github.com/hawkli-1994/django-db-introspection
Author: 李科燃
Author-email: 969543965@qq.com
License: MIT License
Platform: UNKNOWN
Classifier: Environment :: Web Environment
Classifier: Framework :: Django
Classifier: Intended Audience :: Developers
Classifier: License :: OSI Approved :: MIT License
Classifier: Operating System :: OS Independent
Classifier: Programming Language :: Python
Classifier: Programming Language :: Python :: 3.4
Classifier: Programming Language :: Python :: 3.5
Classifier: Programming Language :: Python :: 3.6
Classifier: Topic :: Internet :: WWW/HTTP
